twentytab
