Metadata-Version: 1.0
Name: twentytab-utils
Version: 0.4
Summary: A django app that contains some utilities
Home-page: https://github.com/20tab/twentytab-utils
Author: 20Tab S.r.l.
Author-email: info@20tab.com
License: MIT License
Platform: UNKNOWN
